eomaps/NE_features.json
eomaps/__init__.py
eomaps/_blit_manager.py
eomaps/_containers.py
eomaps/_data_manager.py
eomaps/_maps_base.py
eomaps/_webmap.py
eomaps/annotation_editor.py
eomaps/callbacks.py
eomaps/cb_container.py
eomaps/colorbar.py
eomaps/compass.py
eomaps/draw.py
eomaps/eomaps.py
eomaps/grid.py
eomaps/helpers.py
eomaps/inset_maps.py
eomaps/layout_editor.py
eomaps/logo.png
eomaps/mapsgrid.py
eomaps/ne_features.py
eomaps/projections.py
eomaps/reader.py
eomaps/scalebar.py
eomaps/shapes.py
eomaps/utilities.py
eomaps/webmap_containers.py
eomaps/widgets.py
eomaps/qtcompanion/__init__.py
eomaps/qtcompanion/app.py
eomaps/qtcompanion/base.py
eomaps/qtcompanion/common.py
eomaps/qtcompanion/signal_container.py
eomaps/qtcompanion/icons/close.png
eomaps/qtcompanion/icons/edit_layout.png
eomaps/qtcompanion/icons/edit_layout_active.png
eomaps/qtcompanion/icons/edit_layout_hover.png
eomaps/qtcompanion/icons/eye_closed.png
eomaps/qtcompanion/icons/eye_open.png
eomaps/qtcompanion/icons/info.png
eomaps/qtcompanion/icons/info_checked.png
eomaps/qtcompanion/icons/info_hoover.png
eomaps/qtcompanion/icons/layers.png
eomaps/qtcompanion/icons/layers_hover.png
eomaps/qtcompanion/icons/logo.png
eomaps/qtcompanion/icons/maximize.png
eomaps/qtcompanion/icons/open.png
eomaps/qtcompanion/icons/open_hover.png
eomaps/qtcompanion/icons/peek_bottom.png
eomaps/qtcompanion/icons/peek_bottom_active.png
eomaps/qtcompanion/icons/peek_circle.png
eomaps/qtcompanion/icons/peek_circle_active.png
eomaps/qtcompanion/icons/peek_ellipse.png
eomaps/qtcompanion/icons/peek_ellipse_active.png
eomaps/qtcompanion/icons/peek_left.png
eomaps/qtcompanion/icons/peek_left_active.png
eomaps/qtcompanion/icons/peek_rectangle.png
eomaps/qtcompanion/icons/peek_rectangle_active.png
eomaps/qtcompanion/icons/peek_right.png
eomaps/qtcompanion/icons/peek_right_active.png
eomaps/qtcompanion/icons/peek_square.png
eomaps/qtcompanion/icons/peek_square_active.png
eomaps/qtcompanion/icons/peek_top.png
eomaps-8.3.3.dist-info/licenses/LICENSE
eomaps-8.3.3.dist-info/METADATA
eomaps-8.3.3.dist-info/WHEEL
eomaps-8.3.3.dist-info/entry_points.txt
eomaps-8.3.3.dist-info/top_level.txt
eomaps-8.3.3.dist-info/RECORD
