Metadata-Version: 2.4
Name: eomaps
Version: 8.3.3
Summary: A library to create interactive maps of geographical datasets.
Author-email: Raphael Quast <raphael.quast@geo.tuwien.ac.at>
License: BSD 3-Clause License
Project-URL: Documentation, https://eomaps.readthedocs.io/
Project-URL: Repository, https://github.com/raphaelquast/eomaps
Keywords: Visualization,Plotting,Maps,Geographical Data
Classifier: Programming Language :: Python :: 3
Classifier: License :: OSI Approved :: BSD License
Classifier: Operating System :: OS Independent
Classifier: Framework :: Matplotlib
Classifier: Topic :: Scientific/Engineering
Classifier: Topic :: Scientific/Engineering :: GIS
Classifier: Topic :: Scientific/Engineering :: Visualization
Requires-Python: >=3.8
License-File: LICENSE
Requires-Dist: numpy
Requires-Dist: scipy
Requires-Dist: matplotlib>=3.4
Requires-Dist: cartopy>=0.20.0
Requires-Dist: pyproj
Requires-Dist: packaging
Requires-Dist: click
Provides-Extra: all
Requires-Dist: eomaps[classify,gui,io,shade,wms]; extra == "all"
Provides-Extra: all-nogui
Requires-Dist: eomaps[classify,io,shade,wms]; extra == "all-nogui"
Provides-Extra: io
Requires-Dist: pandas; extra == "io"
Requires-Dist: geopandas; extra == "io"
Requires-Dist: xarray; extra == "io"
Requires-Dist: netcdf4; extra == "io"
Requires-Dist: rioxarray; extra == "io"
Provides-Extra: classify
Requires-Dist: mapclassify; extra == "classify"
Provides-Extra: wms
Requires-Dist: owslib; extra == "wms"
Requires-Dist: requests; extra == "wms"
Provides-Extra: shade
Requires-Dist: datashader; extra == "shade"
Requires-Dist: dask[dataframe]; extra == "shade"
Provides-Extra: gui
Requires-Dist: PyQt5; extra == "gui"
Requires-Dist: qtpy; extra == "gui"
Provides-Extra: test
Requires-Dist: eomaps[classify,gui,io,shade,test,wms]; extra == "test"
Requires-Dist: pytest; extra == "test"
Requires-Dist: pytest-mpl; extra == "test"
Dynamic: license-file
